PIA/__init__.py
PIA/Rockwell/Types.py
PIA/Rockwell/__init__.py
PIA/Rockwell/Util/__init__.py
PIA/Rockwell/Util/Templates/__init__.py
PIA/Rockwell/Util/Templates/Datatypes/Alarm.py
PIA/Rockwell/Util/Templates/Datatypes/PushButton.py
PIA/Rockwell/Util/Templates/Datatypes/__init__.py
PIA/Rockwell/XML/Tools.py
PIA/Rockwell/XML/__init__.py
PIA/Rockwell/XML/Templates/Base_Template.py
PIA/Rockwell/XML/Templates/Controller.py
PIA/Rockwell/XML/Templates/Datatype.py
PIA/Rockwell/XML/Templates/Member.py
PIA/Rockwell/XML/Templates/Program.py
PIA/Rockwell/XML/Templates/Project.py
PIA/Rockwell/XML/Templates/Routine.py
PIA/Rockwell/XML/Templates/Rung.py
PIA/Rockwell/XML/Templates/Tag.py
PIA/Rockwell/XML/Templates/TagComment.py
PIA/Rockwell/XML/Templates/__init__.py
Preh-1.0a2.post0.data/scripts/BuildPBRoutine.py
Preh-1.0a2.post0.dist-info/DESCRIPTION.rst
Preh-1.0a2.post0.dist-info/METADATA
Preh-1.0a2.post0.dist-info/RECORD
Preh-1.0a2.post0.dist-info/WHEEL
Preh-1.0a2.post0.dist-info/metadata.json
Preh-1.0a2.post0.dist-info/top_level.txt
