Metadata-Version: 2.0
Name: Preh
Version: 1.0a2.post0
Summary: Allen-Bradley Python Toolbelt
Home-page: https://bitbucket.org/cmseaton42/allen-bradley-python-tools
Author: Canaan Seaton
Author-email: cmseaton42@gmail.com
License: MIT
Keywords: PLC Tools XML L5X LXML Rockwell Allen Bradley Allen-Bradley Python Python27
Platform: UNKNOWN
Classifier: Development Status :: 3 - Alpha
Classifier: Intended Audience :: Developers
Classifier: Topic :: Software Development :: Build Tools
Classifier: License :: OSI Approved :: MIT License
Classifier: Programming Language :: Python :: 2.7
Requires-Dist: enum
Requires-Dist: lxml (==3.6.0)
